SimEngine-3.7.data/scripts/simengine-cli
enginecore/__init__.py
enginecore/cli/__init__.py
enginecore/cli/configure_state.py
enginecore/cli/model.py
enginecore/cli/power.py
enginecore/cli/status.py
enginecore/cli/storage.py
enginecore/cli/thermal.py
enginecore/model/__init__.py
enginecore/model/graph_reference.py
enginecore/model/query_helpers.py
enginecore/model/supported_sensors.py
enginecore/model/system_modeler.py
enginecore/state/__init__.py
enginecore/state/agents.py
enginecore/state/asset_definition.py
enginecore/state/assets.py
enginecore/state/event_map.py
enginecore/state/events.py
enginecore/state/redis_channels.py
enginecore/state/sensors.py
enginecore/state/state_initializer.py
enginecore/state/state_listener.py
enginecore/state/state_managers.py
enginecore/state/utils.py
enginecore/state/web_socket.py
enginecore/state/agent/__init__.py
enginecore/state/agent/agent.py
enginecore/state/agent/ipmi_agent.py
enginecore/state/agent/snmp_agent.py
enginecore/state/agent/storcli_emu.py
enginecore/state/api/__init__.py
enginecore/state/api/outlet.py
enginecore/state/api/pdu.py
enginecore/state/api/server.py
enginecore/state/api/state.py
enginecore/state/api/static.py
enginecore/state/api/ups.py
enginecore/state/sensor/__init__.py
enginecore/state/sensor/file_locks.py
enginecore/state/sensor/repository.py
enginecore/state/sensor/sensor.py
SimEngine-3.7.dist-info/METADATA
SimEngine-3.7.dist-info/WHEEL
SimEngine-3.7.dist-info/top_level.txt
SimEngine-3.7.dist-info/RECORD
