Metadata-Version: 2.1
Name: SimEngine
Version: 3.7
Summary: Simulation platform for High-Availability systems
Home-page: https://simengine.readthedocs.io/en/latest/
Author: Seneca OSTEP & Alteeve
Author-email: olga.belavina@senecacollege.ca
License: GPL
Project-URL: Bug Tracker, https://github.com/Seneca-CDOT/simengine/issues
Project-URL: Documentation, https://simengine.readthedocs.io/en/latest/
Project-URL: Source Code, https://github.com/Seneca-CDOT/simengine
Platform: UNKNOWN
Classifier: Programming Language :: Python :: 3
Classifier: License :: OSI Approved :: GNU General Public License v3 (GPLv3)
Classifier: Operating System :: POSIX :: Linux
Requires-Dist: redis (>=2.10.6)
Requires-Dist: circuits
Requires-Dist: neo4j-driver
Requires-Dist: pysnmp
Requires-Dist: libvirt-python (==4.1.0)
